scarletio/__init__.py
scarletio/__main__.py
scarletio/websocket.py
scarletio/core/__init__.py
scarletio/core/exceptions.py
scarletio/core/ios.py
scarletio/core/time.py
scarletio/core/event_loop/__init__.py
scarletio/core/event_loop/cycler.py
scarletio/core/event_loop/event_loop.py
scarletio/core/event_loop/event_loop_functionality_helpers.py
scarletio/core/event_loop/event_thread_suspender.py
scarletio/core/event_loop/event_thread_type.py
scarletio/core/event_loop/executor.py
scarletio/core/event_loop/handles.py
scarletio/core/event_loop/selector.py
scarletio/core/event_loop/server.py
scarletio/core/protocols_and_transports/__init__.py
scarletio/core/protocols_and_transports/abstract.py
scarletio/core/protocols_and_transports/extra_info.py
scarletio/core/protocols_and_transports/payload_stream.py
scarletio/core/protocols_and_transports/protocol.py
scarletio/core/protocols_and_transports/ssl_pipe.py
scarletio/core/protocols_and_transports/ssl_transport_layer.py
scarletio/core/protocols_and_transports/transport_layer.py
scarletio/core/protocols_and_transports/unix_pipe_transport_layer.py
scarletio/core/subprocess/__init__.py
scarletio/core/subprocess/subprocess.py
scarletio/core/subprocess/subprocess_protocols.py
scarletio/core/subprocess/subprocess_writer.py
scarletio/core/top_level/__init__.py
scarletio/core/top_level/event_loop.py
scarletio/core/top_level/flow.py
scarletio/core/top_level/task.py
scarletio/core/top_level/trace.py
scarletio/core/traps/__init__.py
scarletio/core/traps/async_executing.py
scarletio/core/traps/event.py
scarletio/core/traps/future.py
scarletio/core/traps/future_chaining.py
scarletio/core/traps/future_repr.py
scarletio/core/traps/future_states.py
scarletio/core/traps/future_wrapper_async.py
scarletio/core/traps/future_wrapper_base.py
scarletio/core/traps/future_wrapper_sync.py
scarletio/core/traps/handle_cancellers.py
scarletio/core/traps/locks.py
scarletio/core/traps/queues.py
scarletio/core/traps/task.py
scarletio-1.0.94.dist-info/LICENSE
scarletio-1.0.94.dist-info/METADATA
scarletio-1.0.94.dist-info/WHEEL
scarletio-1.0.94.dist-info/entry_points.txt
scarletio-1.0.94.dist-info/top_level.txt
scarletio-1.0.94.dist-info/RECORD
