Metadata-Version: 2.1
Name: scarletio
Version: 1.0.94
Summary: Asynchronous blackmagic & Witchcraft
Home-page: https://github.com/HuyaneMatsu/scarletio
Author: HuyaneMatsu
Author-email: re.ism.tm@gmail.com
License: DBAD
Platform: UNKNOWN
Classifier: Development Status :: 4 - Beta
Classifier: Intended Audience :: Developers
Classifier: Operating System :: POSIX :: Linux
Classifier: Programming Language :: Python
Classifier: Programming Language :: Python :: 3.6
Classifier: Programming Language :: Python :: 3.7
Classifier: Programming Language :: Python :: 3.8
Classifier: Programming Language :: Python :: 3.9
Classifier: Programming Language :: Python :: 3.10
Classifier: Programming Language :: Python :: 3.11
Classifier: Programming Language :: Python :: Implementation :: CPython
Classifier: Programming Language :: Python :: Implementation :: PyPy
Classifier: Topic :: Software Development :: Libraries
Classifier: Topic :: Software Development :: Libraries :: Python Modules
Requires-Python: >=3.6
Requires-Dist: chardet (>=2.0)
Provides-Extra: cpythonspeedups
Requires-Dist: cchardet (>=2.0) ; extra == 'cpythonspeedups'
